flask_openapi_rapidoc/__init__.py
flask_openapi_rapidoc/__version__.py
flask_openapi_rapidoc/plugins.py
flask_openapi_rapidoc/templates/__init__.py
flask_openapi_rapidoc/templates/rapidoc/images/rapidoc.svg
flask_openapi_rapidoc/templates/rapidoc/js/rapidoc-min.js
flask_openapi_rapidoc-9.3.8.dist-info/METADATA
flask_openapi_rapidoc-9.3.8.dist-info/WHEEL
flask_openapi_rapidoc-9.3.8.dist-info/entry_points.txt
flask_openapi_rapidoc-9.3.8.dist-info/RECORD
